README.rst
setup.cfg
setup.py
lx_pylib.egg-info/PKG-INFO
lx_pylib.egg-info/SOURCES.txt
lx_pylib.egg-info/dependency_links.txt
lx_pylib.egg-info/top_level.txt
pylib/__init__.py
pylib/_compat.py
pylib/security.py
pylib/string.py
pylib/version.py