Metadata-Version: 1.0
Name: lx-pylib
Version: 0.3.0
Summary: Some useful python utils
Home-page: https://github.com/hilarryxu/lx-pylib
Author: Larry Xu
Author-email: hilarryxu@gmail.com
License: BSD
Platform: UNKNOWN
